relative_dose_1d/GUI.py
relative_dose_1d/GUI_tool.py
relative_dose_1d/__init__.py
relative_dose_1d/tools.py
relative_dose_1d/test_data/clean.py
relative_dose_1d-0.1.7.dist-info/LICENSE
relative_dose_1d-0.1.7.dist-info/METADATA
relative_dose_1d-0.1.7.dist-info/WHEEL
relative_dose_1d-0.1.7.dist-info/top_level.txt
relative_dose_1d-0.1.7.dist-info/RECORD
