Metadata-Version: 2.1
Name: relative-dose-1d
Version: 0.1.7
Summary: Python package to read 1-dimensional dose profile from a text file to perform subtraction and gamma analysis.
Author-email: Luis Alfonso Olivares Jimenez <alfonso.cucei.udg@gmail.com>
Project-URL: homepage, https://relative-dose-1d.readthedocs.io/en/latest/intro.html
Project-URL: repository, https://github.com/LuisOlivaresJ/relative_dose_1d
Project-URL: Bug-Tracker, https://github.com/LuisOlivaresJ/relative_dose_1d/issues
Keywords: Radiotherapy,Relative dose distribution,gamma index,python,w2CAD,mcc
Classifier: Programming Language :: Python :: 3
Classifier: Operating System :: OS Independent
Classifier: Intended Audience :: Science/Research
Classifier: Intended Audience :: Education
Classifier: Intended Audience :: Healthcare Industry
Classifier: Topic :: Scientific/Engineering :: Medical Science Apps.
Classifier: Topic :: Scientific/Engineering :: Physics
Classifier: Natural Language :: Spanish
Requires-Python: >=3.7
License-File: LICENSE
Requires-Dist: numpy (>=1.23.4)
Requires-Dist: matplotlib (>=3.6.1)
Requires-Dist: PyQt6 (>=6.4.2)
